qlc/install.py
qlc/__init__.py
qlc/doc/CAMS_b2ro-b2rn_20181201-20181221_qlc_Z1-png_202509090814.pdf
qlc/doc/CONTRIBUTING.md
qlc/doc/EVALTOOLS.md
qlc/doc/USAGE.md
qlc/doc/README.md
qlc/doc/INSTALL_DEV.md
qlc/examples/cams_case_1/obs/ebas_station-locations.csv
qlc/examples/cams_case_1/obs/ebas_daily/v_20240216/201812/ebas_20181205.nc
qlc/examples/cams_case_1/obs/ebas_daily/v_20240216/201812/ebas_20181209.nc
qlc/examples/cams_case_1/obs/ebas_daily/v_20240216/201812/ebas_20181208.nc
qlc/examples/cams_case_1/obs/ebas_daily/v_20240216/201812/ebas_20181201.nc
qlc/examples/cams_case_1/obs/ebas_daily/v_20240216/201812/ebas_20181218.nc
qlc/examples/cams_case_1/obs/ebas_daily/v_20240216/201812/ebas_20181221.nc
qlc/examples/cams_case_1/obs/ebas_daily/v_20240216/201812/ebas_20181213.nc
qlc/examples/cams_case_1/obs/ebas_daily/v_20240216/201812/ebas_20181203.nc
qlc/examples/cams_case_1/obs/ebas_daily/v_20240216/201812/ebas_20181223.nc
qlc/examples/cams_case_1/obs/ebas_daily/v_20240216/201812/ebas_20181202.nc
qlc/examples/cams_case_1/obs/ebas_daily/v_20240216/201812/ebas_20181212.nc
qlc/examples/cams_case_1/obs/ebas_daily/v_20240216/201812/ebas_20181217.nc
qlc/examples/cams_case_1/obs/ebas_daily/v_20240216/201812/ebas_20181228.nc
qlc/examples/cams_case_1/obs/ebas_daily/v_20240216/201812/ebas_20181227.nc
qlc/examples/cams_case_1/obs/ebas_daily/v_20240216/201812/ebas_20181206.nc
qlc/examples/cams_case_1/obs/ebas_daily/v_20240216/201812/ebas_20181210.nc
qlc/examples/cams_case_1/obs/ebas_daily/v_20240216/201812/ebas_20181204.nc
qlc/examples/cams_case_1/obs/ebas_daily/v_20240216/201812/ebas_20181207.nc
qlc/examples/cams_case_1/obs/ebas_daily/v_20240216/201812/ebas_20181229.nc
qlc/examples/cams_case_1/obs/ebas_daily/v_20240216/201812/ebas_20181214.nc
qlc/examples/cams_case_1/obs/ebas_daily/v_20240216/201812/ebas_20181216.nc
qlc/examples/cams_case_1/obs/ebas_daily/v_20240216/201812/ebas_20181224.nc
rc_qlc-0.4.2.dist-info/WHEEL
rc_qlc-0.4.2.dist-info/entry_points.txt
rc_qlc-0.4.2.dist-info/top_level.txt
rc_qlc-0.4.2.dist-info/METADATA
rc_qlc-0.4.2.dist-info/RECORD
rc_qlc-0.4.2.dist-info/licenses/LICENSE
