Metadata-Version: 2.4
Name: rc-qlc
Version: 0.4.2
Summary: Quick Look Content (QLC): An Automated Model–Observation Comparison Suite Optimized for CAMS [BETA]
Home-page: https://pypi.org/project/qlc/
Author-email: ResearchConcepts io GmbH <contact@researchconcepts.io>
License: MIT
Requires-Python: >=3.10
License-File: LICENSE
Requires-Dist: numpy<2.0,>=1.21.0
Requires-Dist: pandas
Requires-Dist: matplotlib
Requires-Dist: seaborn
Requires-Dist: xarray
Requires-Dist: netCDF4
Requires-Dist: dask[complete]
Requires-Dist: scipy
Requires-Dist: cartopy
Requires-Dist: tqdm
Requires-Dist: adjustText
Requires-Dist: cftime
Requires-Dist: bottleneck
Requires-Dist: tomli; python_version < "3.11"
Provides-Extra: build
Requires-Dist: tomli; extra == "build"
Requires-Dist: pyproject-hooks; extra == "build"
Requires-Dist: twine; extra == "build"
Provides-Extra: test
Requires-Dist: pytest; extra == "test"
Provides-Extra: dev
Requires-Dist: tomli; extra == "dev"
Requires-Dist: pyproject-hooks; extra == "dev"
Requires-Dist: keyring; extra == "dev"
Requires-Dist: readme-renderer; extra == "dev"
Requires-Dist: requests; extra == "dev"
Requires-Dist: requests-toolbelt; extra == "dev"
Requires-Dist: rfc3986; extra == "dev"
Requires-Dist: rich; extra == "dev"
Requires-Dist: urllib3; extra == "dev"
Requires-Dist: twine; extra == "dev"
Provides-Extra: cams
Dynamic: home-page
Dynamic: license-file
